pwntrace/__init__.py
pwntrace/heap_ltrace.py
pwntrace/ltrace.py
pwntrace-1.0.0.dist-info/DESCRIPTION.rst
pwntrace-1.0.0.dist-info/METADATA
pwntrace-1.0.0.dist-info/RECORD
pwntrace-1.0.0.dist-info/WHEEL
pwntrace-1.0.0.dist-info/metadata.json
pwntrace-1.0.0.dist-info/top_level.txt
