Metadata-Version: 2.0
Name: pwntrace
Version: 1.0.0
Summary: Use ltrace with pwnlib.tubes.process instances
Home-page: https://github.com/andreafioraldi/pwntrace
Author: Andrea Fioraldi
Author-email: andreafioraldi@gmail.com
License: MIT
Download-URL: https://github.com/andreafioraldi/pwntrace/archive/1.0.0.tar.gz
Platform: UNKNOWN
Requires-Dist: pwn
